WebsocketTest/__init__.py
WebsocketTest/allure_installer.py
WebsocketTest/cli.py
WebsocketTest/conftest.py
WebsocketTest/run_tests.py
WebsocketTest/caseScript/Aiui.py
WebsocketTest/caseScript/Aqua.py
WebsocketTest/caseScript/Gateway.py
WebsocketTest/caseScript/__init__.py
WebsocketTest/commands/__init__.py
WebsocketTest/commands/report.py
WebsocketTest/commands/startproject.py
WebsocketTest/commands/test.py
WebsocketTest/common/Assertion.py
WebsocketTest/common/PyTestRunner.py
WebsocketTest/common/WSBaseApi.py
WebsocketTest/common/__init__.py
WebsocketTest/common/assertUtils.py
WebsocketTest/common/logger.py
WebsocketTest/common/utils.py
WebsocketTest/libs/allure-2.30.0.zip
WebsocketTest/templates/basic/README.md
WebsocketTest/templates/basic/conftest.py1
WebsocketTest/templates/basic/pytest.ini
WebsocketTest/templates/basic/__pycache__/conftest.cpython-310-pytest-8.3.5.pyc
WebsocketTest/templates/basic/config/appConfig.yml
WebsocketTest/templates/basic/config/audi/live.yml
WebsocketTest/templates/basic/config/audi/uat.yml
WebsocketTest/templates/basic/config/audi/aqua/live.yml
WebsocketTest/templates/basic/config/audi/aqua/uat.yml
WebsocketTest/templates/basic/config/svw/live.yml
WebsocketTest/templates/basic/config/svw/uat.yml
WebsocketTest/templates/basic/config/svw/aqua/live.yml
WebsocketTest/templates/basic/config/svw/aqua/uat.yml
WebsocketTest/templates/basic/config/svw/gateway_5.0/live.yml
WebsocketTest/templates/basic/config/svw/gateway_5.0/uat.yml
WebsocketTest/templates/basic/config/vwa/live.yml
WebsocketTest/templates/basic/config/vwa/uat.yml
WebsocketTest/templates/basic/config/vwa/aqua/live.yml
WebsocketTest/templates/basic/config/vwa/aqua/uat.yml
WebsocketTest/templates/basic/config/vwa/gateway_5.0/live.yml
WebsocketTest/templates/basic/config/vwa/gateway_5.0/uat.yml
WebsocketTest/templates/basic/config/vwa/gateway_5.4/live.yml
WebsocketTest/templates/basic/config/vwa/gateway_5.4/uat.yml
WebsocketTest/templates/basic/data/case_data.xlsx
websockettest-1.0.20.dist-info/METADATA
websockettest-1.0.20.dist-info/WHEEL
websockettest-1.0.20.dist-info/entry_points.txt
websockettest-1.0.20.dist-info/top_level.txt
websockettest-1.0.20.dist-info/RECORD
