Metadata-Version: 2.4
Name: WebsocketTest
Version: 1.0.20
Summary: websocket api autotest
Requires-Dist: allure-pytest>=2.13.5
Requires-Dist: pandas>=2.2.3
Requires-Dist: pytest>=8.2.2
Requires-Dist: PyYAML>=6.0.2
Requires-Dist: websockets>=12.0
Requires-Dist: pytest-rerunfailures>=15.0
Dynamic: requires-dist
Dynamic: summary
